hs.admin.api-0.3-py3.10-nspkg.pth
hs/admin/api/__init__.py
hs/admin/api/api.py
hs/admin/api/dispatcher.py
hs/admin/api/exceptions.py
hs/admin/api/method.py
hs/admin/api/module.py
hs/admin/api/proxy.py
hs/admin/api/session.py
hs.admin.api-0.3.dist-info/METADATA
hs.admin.api-0.3.dist-info/WHEEL
hs.admin.api-0.3.dist-info/namespace_packages.txt
hs.admin.api-0.3.dist-info/top_level.txt
hs.admin.api-0.3.dist-info/RECORD
