Metadata-Version: 2.1
Name: hs.admin.api
Version: 0.3
Summary: Hostsharing HSAdmin API
Home-page: https://www.hostsharing.net
Author: Hostsharing eG
Author-email: info@hostsharing.net
License: lgpl
Keywords: Hostsharing HSAdmin API
Classifier: Programming Language :: Python
Requires-Dist: setuptools
Requires-Dist: requests
Requires-Dist: pyyaml
